ebookmeta/__init__.py
ebookmeta/epub2.py
ebookmeta/epub3.py
ebookmeta/exceptions.py
ebookmeta/fb2.py
ebookmeta/fb2genres.py
ebookmeta/metadata.py
ebookmeta/myzipfile.py
ebookmeta/utils.py
ebookmeta-1.2.11.dist-info/LICENSE.txt
ebookmeta-1.2.11.dist-info/METADATA
ebookmeta-1.2.11.dist-info/WHEEL
ebookmeta-1.2.11.dist-info/top_level.txt
ebookmeta-1.2.11.dist-info/RECORD
