Metadata-Version: 2.1
Name: ebookmeta
Version: 1.2.11
Summary: Read/write ebook metadata for fb2, epub2 and epub3 files
Home-page: https://github.com/dnkorpushov/ebookmeta
Author: Dmitrii Korpushov
Author-email: dnkorpushov@gmail.com
License: MIT
Keywords: ebook,epub,metadata,fb2
Classifier: Operating System :: OS Independent
Classifier: Topic :: Software Development
Classifier: Programming Language :: Python :: 3.3
Classifier: Programming Language :: Python :: 3.4
Classifier: Programming Language :: Python :: 3.5
Classifier: Programming Language :: Python :: 3.6
Classifier: Programming Language :: Python :: 3.7
Classifier: Programming Language :: Python :: 3.8
Classifier: Programming Language :: Python :: 3.9
Classifier: Topic :: Software Development :: Libraries :: Python Modules
License-File: LICENSE.txt
